reacter_openapitools/__init__.py
reacter_openapitools/_anthropic_adapter.py
reacter_openapitools/_base_adapter.py
reacter_openapitools/_langchain_adapter.py
reacter_openapitools/_openai_adapter.py
reacter_openapitools-0.1.1.dist-info/licenses/LICENSE
reacter_openapitools-0.1.1.dist-info/METADATA
reacter_openapitools-0.1.1.dist-info/WHEEL
reacter_openapitools-0.1.1.dist-info/top_level.txt
reacter_openapitools-0.1.1.dist-info/RECORD
