Metadata-Version: 2.4
Name: reacter-openapitools
Version: 0.1.1
Summary: Python package for openapitools
Author-email: Sankar kvs <openapitools@gmail.com>
License: MIT
Project-URL: Homepage, https://github.com/kvssankar/openapitools-sdk-py
Project-URL: Bug Tracker, https://github.com/kvssankar/openapitools-sdk-py/issues
Project-URL: Documentation, https://docs.openapitools.com
Classifier: Programming Language :: Python :: 3
Classifier: License :: OSI Approved :: MIT License
Classifier: Operating System :: OS Independent
Requires-Python: >=3.8
License-File: LICENSE
Dynamic: license-file
Dynamic: requires-python
